odoo/addons/l10n_ro_stock_account_mrp/README.rst
odoo/addons/l10n_ro_stock_account_mrp/__init__.py
odoo/addons/l10n_ro_stock_account_mrp/__manifest__.py
odoo/addons/l10n_ro_stock_account_mrp/i18n/l10n_ro_stock_account_mrp.pot
odoo/addons/l10n_ro_stock_account_mrp/i18n/ro.po
odoo/addons/l10n_ro_stock_account_mrp/models/__init__.py
odoo/addons/l10n_ro_stock_account_mrp/models/mrp_unbuild.py
odoo/addons/l10n_ro_stock_account_mrp/readme/CONTRIBUTORS.rst
odoo/addons/l10n_ro_stock_account_mrp/readme/DESCRIPTION.rst
odoo/addons/l10n_ro_stock_account_mrp/static/description/icon.png
odoo/addons/l10n_ro_stock_account_mrp/static/description/index.html
odoo/addons/l10n_ro_stock_account_mrp/tests/__init__.py
odoo/addons/l10n_ro_stock_account_mrp/tests/test_valuation_layers.py
odoo/addons/l10n_ro_stock_account_mrp/views/mrp_unbuild_views.xml
odoo_addon_l10n_ro_stock_account_mrp-16.0.0.4.0.dist-info/METADATA
odoo_addon_l10n_ro_stock_account_mrp-16.0.0.4.0.dist-info/WHEEL
odoo_addon_l10n_ro_stock_account_mrp-16.0.0.4.0.dist-info/top_level.txt
odoo_addon_l10n_ro_stock_account_mrp-16.0.0.4.0.dist-info/RECORD
