Metadata-Version: 2.1
Name: odoo-addon-l10n-ro-stock-account-mrp
Version: 16.0.0.4.0
Summary: Fix mrp_production cost.
Home-page: https://github.com/OCA/l10n-romania
Author: Dakai Soft SRL,Odoo Community Association (OCA)
Author-email: support@odoo-community.org
License: AGPL-3
Platform: UNKNOWN
Classifier: Programming Language :: Python
Classifier: Framework :: Odoo
Classifier: Framework :: Odoo :: 16.0
Classifier: License :: OSI Approved :: GNU Affero General Public License v3
Classifier: Development Status :: 6 - Mature
Requires-Python: >=3.10
Requires-Dist: odoo-addon-l10n-ro-stock-account <16.1dev,>=16.0dev
Requires-Dist: odoo <16.1dev,>=16.0a
